ganf/__init__.py
ganf/cli.py
ganf/config.py
ganf/exceptions.py
ganf/segment.py
ganf/translator.py
ganf/util.py
ganf-1.0.2a0.dist-info/entry_points.txt
ganf-1.0.2a0.dist-info/METADATA
ganf-1.0.2a0.dist-info/WHEEL
ganf-1.0.2a0.dist-info/RECORD
